signalkit/__init__.py
signalkit/__init__.pyi
signalkit/core.py
signalkit/core.pyi
signalkit/py.typed
signalkit-2.5.0.dist-info/METADATA
signalkit-2.5.0.dist-info/WHEEL
signalkit-2.5.0.dist-info/top_level.txt
signalkit-2.5.0.dist-info/RECORD
