Metadata-Version: 2.4
Name: signalkit
Version: 2.5.0
Summary: Structured, UUID-based signal orchestration utilities for Python using Blinker
Author-email: KMRH47 <kmrh47@pm.me>
Requires-Python: >=3.8
Requires-Dist: blinker
